LICENSE
README.txt
development.ini
setup.cfg
setup.py
test.ini
byCycleTripPlanner.egg-info/PKG-INFO
byCycleTripPlanner.egg-info/SOURCES.txt
byCycleTripPlanner.egg-info/dependency_links.txt
byCycleTripPlanner.egg-info/entry_points.txt
byCycleTripPlanner.egg-info/not-zip-safe
byCycleTripPlanner.egg-info/paste_deploy_config.ini_tmpl
byCycleTripPlanner.egg-info/paster_plugins.txt
byCycleTripPlanner.egg-info/requires.txt
byCycleTripPlanner.egg-info/top_level.txt
script/restart
script/start
script/stop
script/tail
service/production.ini
service/serve.py
service/tripplanner-four/run
service/tripplanner-four/log/run
service/tripplanner-one/httpd-vhosts.conf
service/tripplanner-one/httpd.conf
service/tripplanner-one/run
service/tripplanner-one/log/run
service/tripplanner-three/run
service/tripplanner-three/log/run
service/tripplanner-two/run
service/tripplanner-two/log/run
tripplanner/__init__.py
tripplanner/websetup.py
tripplanner/config/__init__.py
tripplanner/config/environment.py
tripplanner/config/middleware.py
tripplanner/config/routing.py
tripplanner/controllers/__init__.py
tripplanner/controllers/ads.py
tripplanner/controllers/error.py
tripplanner/controllers/geocodes.py
tripplanner/controllers/regions.py
tripplanner/controllers/routes.py
tripplanner/controllers/services.py
tripplanner/controllers/template.py
tripplanner/docs/index.txt
tripplanner/i18n/__init__.py
tripplanner/lib/__init__.py
tripplanner/lib/app_globals.py
tripplanner/lib/base.py
tripplanner/lib/helpers.py
tripplanner/models/__init__.py
tripplanner/public/favicon.ico
tripplanner/public/robots.txt
tripplanner/public/images/crosshair4.gif
tripplanner/public/images/dd-end.png
tripplanner/public/images/dd-start.png
tripplanner/public/images/logo.png
tripplanner/public/images/logo.svg
tripplanner/public/images/markerC.png
tripplanner/public/images/powered_by.png
tripplanner/public/images/pylons-tower-dark1.png
tripplanner/public/images/reddot15.png
tripplanner/public/images/reddot15.svg
tripplanner/public/images/shadow50.png
tripplanner/public/images/spinner.gif
tripplanner/public/images/swapfrto.gif
tripplanner/public/images/swapfrto.png
tripplanner/public/images/transparent.png
tripplanner/public/images/valid-css.png
tripplanner/public/images/valid-xhtml.png
tripplanner/public/images/x.png
tripplanner/public/images/portlandor/map_legend.png
tripplanner/public/images/restler/powered_by.png
